{
  "goal": "创建一个名为test_fix.txt的文件，内容为：JSON parsing fixed!",
  "phases": [
    {
      "id": 1,
      "title": "需求分析",
      "description": "深入理解用户需求，识别关键要素",
      "capabilities": {},
      "status": "completed",
      "result": "思考完成",
      "error": null
    },
    {
      "id": 2,
      "title": "方案设计",
      "description": "设计解决方案，规划执行步骤",
      "capabilities": {},
      "status": "completed",
      "result": "思考完成",
      "error": null
    },
    {
      "id": 3,
      "title": "资源准备",
      "description": "准备必要的工具、数据和环境",
      "capabilities": {},
      "status": "completed",
      "result": "思考完成",
      "error": null
    },
    {
      "id": 4,
      "title": "执行实施",
      "description": "按照方案执行具体操作",
      "capabilities": {},
      "status": "completed",
      "result": "已完成 1 个步骤",
      "error": null
    },
    {
      "id": 5,
      "title": "测试验证",
      "description": "测试执行结果，验证是否达标",
      "capabilities": {},
      "status": "completed",
      "result": "已完成 2 个步骤",
      "error": null
    },
    {
      "id": 6,
      "title": "交付总结",
      "description": "整理结果，交付给用户",
      "capabilities": {},
      "status": "completed",
      "result": "思考完成",
      "error": null
    }
  ],
  "current_phase_id": 6,
  "status": "completed"
}