{
  "goal": "贾维斯,按照我教你的方法,自己添加浏览器工具:1.搜索方案 2.学习使用 3.创建模块 4.注册工具 5.测试 6.同步GitHub",
  "understanding": "用户希望我为贾维斯智能代理添加浏览器自动化功能（包括导航、点击、输入、滚动等），以便访问和分析Manus界面，进而完成当前UI与Manus界面的差异分析，并设计实时日志显示功能。用户明确要求先提交详细方案，包含UI差异分析、技术设计、文件清单和实施步骤。同时，用户偏好禁止批量操作，UI和配置修改需确认，删除操作必须确认，且风险容忍度为中等，出错需自动回滚。",
  "approach": "分阶段实现浏览器自动化功能并完成UI差异分析与实时日志显示功能设计",
  "iteration": 4,
  "risk_assessment": "medium",
  "steps": [
    {
      "id": "扫描项目根目录，确认当前UI界面文件ui.html的存在及路径",
      "tool": "scan_files",
      "status": "done"
    },
    {
      "id": "扫描项目根目录，定位Manus界面相关文件及路径",
      "tool": "scan_files",
      "status": "done"
    },
    {
      "id": "读取当前UI界面文件内容，分析其结构和功能实现",
      "tool": "read_file",
      "status": "done"
    },
    {
      "id": "读取Manus界面文件内容，分析其结构和功能实现",
      "tool": "read_file",
      "status": "done"
    },
    {
      "id": "启动安全自我修改会话，为添加浏览器自动化功能做准备",
      "tool": "self_modify_start",
      "status": "pending"
    },
    {
      "id": "编写浏览器自动化模块代码",
      "tool": "self_modify_write",
      "status": "pending"
    },
    {
      "id": "测试浏览器自动化模块功能，确保导航、点击、输入、滚动等操作正常",
      "tool": "self_modify_test",
      "status": "pending"
    },
    {
      "id": "应用浏览器自动化模块修改",
      "tool": "self_modify_apply",
      "status": "pending"
    },
    {
      "id": "结束自我修改会话",
      "tool": "self_modify_end",
      "status": "pending"
    },
    {
      "id": "使用新增浏览器自动化功能动态访问Manus界面，获取UI信息",
      "tool": "run_python",
      "status": "pending"
    },
    {
      "id": "分析UI和Manus界面代码结构和功能差异",
      "tool": "analyze_code",
      "status": "pending"
    },
    {
      "id": "生成详细方案文档供用户确认",
      "tool": "write_file",
      "status": "pending"
    },
    {
      "id": "确认是否允许修改UI文件及新增实时日志显示功能，遵循用户确认要求",
      "tool": "confirm_delete",
      "status": "pending"
    }
  ]
}